apiman/__init__.py
apiman/base.py
apiman/bottle.py
apiman/django.py
apiman/falcon.py
apiman/flask.py
apiman/starlette.py
apiman/static/index.html
apiman/static/openapi2_schema.json
apiman/static/openapi3.1_schema.yaml
apiman/static/redoc.html
apiman/static/swagger.html
apiman/static/template.yaml
apiman/tornado.py
apiman-0.5.4.dist-info/LICENSE
apiman-0.5.4.dist-info/METADATA
apiman-0.5.4.dist-info/WHEEL
apiman-0.5.4.dist-info/RECORD
