Metadata-Version: 2.1
Name: apiman
Version: 0.5.4
Summary: Integrate api manual for your web project
Home-page: https://github.com/strongbugman/apiman
License: BSD
Author: strongbugman
Author-email: strongbugman@gmail.com
Requires-Python: >=3.7,<4
Classifier: Environment :: Console
Classifier: License :: Other/Proprietary License
Classifier: Programming Language :: Python :: 3
Classifier: Programming Language :: Python :: 3.7
Classifier: Programming Language :: Python :: 3.8
Classifier: Programming Language :: Python :: 3.9
Classifier: Programming Language :: Python :: 3.10
Classifier: Programming Language :: Python :: 3.11
Classifier: Topic :: Internet :: WWW/HTTP
Classifier: Topic :: Software Development :: Libraries :: Application Frameworks
Classifier: Topic :: Software Development :: Libraries :: Python Modules
Requires-Dist: Jinja2 (>=3.0.2)
Requires-Dist: PyYAML (>=6.0)
Requires-Dist: jsonschema-rs (>=0.13.0)
Requires-Dist: xmltodict (>=0.13.0)
Project-URL: Repository, https://github.com/strongbugman/apiman
